gmshModel/__init__.py
gmshModel/_version.py
gmshModel/Geometry/DistanceCalculations.py
gmshModel/Geometry/GeometricObjects.py
gmshModel/Geometry/__init__.py
gmshModel/MeshExport/MeshExport.py
gmshModel/MeshExport/__init__.py
gmshModel/Model/BodyCenteredCubicCell.py
gmshModel/Model/FaceCenteredCubicCell.py
gmshModel/Model/GenericModel.py
gmshModel/Model/GenericRVE.py
gmshModel/Model/GenericUnitCell.py
gmshModel/Model/HelicalChain.py
gmshModel/Model/HexagonalCell.py
gmshModel/Model/InclusionRVE.py
gmshModel/Model/RandomInclusionRVE.py
gmshModel/Model/SimpleCubicCell.py
gmshModel/Model/__init__.py
gmshModel/Visualization/GeometryVisualization.py
gmshModel/Visualization/MeshVisualization.py
gmshModel/Visualization/__init__.py
gmshModel-1.1.1.dist-info/LICENSE
gmshModel-1.1.1.dist-info/METADATA
gmshModel-1.1.1.dist-info/WHEEL
gmshModel-1.1.1.dist-info/top_level.txt
gmshModel-1.1.1.dist-info/RECORD
