Metadata-Version: 2.1
Name: gmshModel
Version: 1.1.1
Summary: A mesh modeling interface to the Gmsh-Python-API
Home-page: https://github.com/NEFM-TUDresden/GmshModel
Author: Philipp Metsch
Author-email: philipp.metsch@tu-dresden.de
Project-URL: Code, https://github.com/NEFM-TUDresden/GmshModel
Project-URL: Issues, https://github.com/NEFM-TUDresden/GmshModel/issues
Project-URL: Documentation, https://gmshmodel.readthedocs.io/en/latest/
Keywords: Gmsh mesh preprocessing
Classifier: Development Status :: 5 - Production/Stable
Classifier: Intended Audience :: Developers
Classifier: Intended Audience :: Science/Research
Classifier: Programming Language :: Python :: 3
Classifier: Programming Language :: Python :: 3.5
Classifier: Programming Language :: Python :: 3.6
Classifier: Programming Language :: Python :: 3.7
Classifier: Programming Language :: Python :: 3.8
Classifier: Programming Language :: Python :: 3.9
Classifier: Programming Language :: Python :: 3.10
Classifier: License :: OSI Approved :: GNU General Public License v3 or later (GPLv3+)
Classifier: Topic :: Scientific/Engineering
Classifier: Topic :: Utilities
Requires-Python: >=3.5
License-File: LICENSE
Requires-Dist: numpy
Requires-Dist: gmsh
Requires-Dist: meshio[all] <=5.1.2,>=4
Requires-Dist: pyvista >=0.24.1
